thingspire/__init__.py
thingspire/datasets/__init__.py
thingspire/datasets/resource-id-name.py
thingspire/datasets/ts_calendar.py
thingspire/datasets/ts_region.py
thingspire/datasets/ts_weather.py
thingspire/datasets/utils.py
thingspire_datasets-0.1.7.dist-info/METADATA
thingspire_datasets-0.1.7.dist-info/WHEEL
thingspire_datasets-0.1.7.dist-info/top_level.txt
thingspire_datasets-0.1.7.dist-info/RECORD
